swiss_pollen/__init__.py
swiss_pollen/main.py
tests/__init__.py
tests/test___init__.py
tests/test_pollen_service_integration.py
swiss_pollen-1.1.0.dist-info/LICENSE.txt
swiss_pollen-1.1.0.dist-info/METADATA
swiss_pollen-1.1.0.dist-info/WHEEL
swiss_pollen-1.1.0.dist-info/entry_points.txt
swiss_pollen-1.1.0.dist-info/top_level.txt
swiss_pollen-1.1.0.dist-info/RECORD
