Metadata-Version: 2.1
Name: swiss-pollen
Version: 1.1.0
Summary: API to gather the current pollen load from MeteoSchweiz
Home-page: https://github.com/frimtec/swiss-pollen
Author: Markus Friedli
Author-email: frimtec@gmx.ch
License: Apache-2.0
Keywords: pollen swiss
Classifier: Programming Language :: Python :: 3
Classifier: Operating System :: OS Independent
Requires-Python: >=3.9
License-File: LICENSE.txt
Requires-Dist: requests
Requires-Dist: pytz
